{
    "Ar36": {
        "error": 0.00027759619412553646,
        "error_type": "SEM",
        "filter_outliers_dict": {
            "filter_outliers": true,
            "iterations": 1,
            "std_devs": 3,
            "use_iqr_filtering": false,
            "use_standard_deviation_filtering": false
        },
        "fit": "linear",
        "fn": 122,
        "include_baseline_error": true,
        "n": 122,
        "outlier_excluded": [],
        "reviewed": true,
        "user_excluded": [],
        "value": 0.009808486880117321
    },
    "Ar37": {
        "error": 0.006684958829096409,
        "error_type": "SEM",
        "filter_outliers_dict": {
            "filter_outliers": true,
            "iterations": 1,
            "std_devs": 3,
            "use_iqr_filtering": false,
            "use_standard_deviation_filtering": false
        },
        "fit": "linear",
        "fn": 122,
        "include_baseline_error": true,
        "n": 122,
        "outlier_excluded": [],
        "reviewed": true,
        "user_excluded": [],
        "value": 0.07601133018435581
    },
    "Ar38": {
        "error": 0.005356880359016358,
        "error_type": "SEM",
        "filter_outliers_dict": {
            "filter_outliers": true,
            "iterations": 1,
            "std_devs": 3,
            "use_iqr_filtering": false,
            "use_standard_deviation_filtering": false
        },
        "fit": "linear",
        "fn": 121,
        "include_baseline_error": true,
        "n": 122,
        "outlier_excluded": [
            48
        ],
        "reviewed": true,
        "user_excluded": [],
        "value": 0.08976466758498923
    },
    "Ar39": {
        "error": 0.012852425215167504,
        "error_type": "SEM",
        "filter_outliers_dict": {
            "filter_outliers": true,
            "iterations": 1,
            "std_devs": 3,
            "use_iqr_filtering": false,
            "use_standard_deviation_filtering": false
        },
        "fit": "linear",
        "fn": 121,
        "include_baseline_error": true,
        "n": 122,
        "outlier_excluded": [
            60
        ],
        "reviewed": true,
        "user_excluded": [],
        "value": 5.493221352670561
    },
    "Ar40": {
        "error": 0.015578555964830581,
        "error_type": "SEM",
        "filter_outliers_dict": {
            "filter_outliers": true,
            "iterations": 1,
            "std_devs": 3,
            "use_iqr_filtering": false,
            "use_standard_deviation_filtering": false
        },
        "fit": "linear",
        "fn": 122,
        "include_baseline_error": true,
        "n": 122,
        "outlier_excluded": [],
        "reviewed": true,
        "user_excluded": [],
        "value": 25.96945794897347
    },
    "Ar41": {
        "error": 0.05624044418940154,
        "error_type": "SEM",
        "filter_outliers_dict": {
            "filter_outliers": true,
            "iterations": 1,
            "std_devs": 2
        },
        "fit": "linear",
        "value": -0.7288846156141944
    }
}