{
    "Ar36": {
        "error": 0.0003350216583931128,
        "error_type": "SEM",
        "filter_outliers_dict": {
            "filter_outliers": true,
            "iterations": 1,
            "std_devs": 3,
            "use_iqr_filtering": false,
            "use_standard_deviation_filtering": false
        },
        "fit": "linear",
        "fn": 122,
        "include_baseline_error": true,
        "n": 122,
        "outlier_excluded": [],
        "reviewed": true,
        "user_excluded": [],
        "value": 0.016206406267524218
    },
    "Ar37": {
        "error": 0.0068302916390031235,
        "error_type": "SEM",
        "filter_outliers_dict": {
            "filter_outliers": true,
            "iterations": 1,
            "std_devs": 3,
            "use_iqr_filtering": false,
            "use_standard_deviation_filtering": false
        },
        "fit": "linear",
        "fn": 122,
        "include_baseline_error": true,
        "n": 122,
        "outlier_excluded": [],
        "reviewed": true,
        "user_excluded": [],
        "value": 0.008059814571573266
    },
    "Ar38": {
        "error": 0.006134696284472794,
        "error_type": "SEM",
        "filter_outliers_dict": {
            "filter_outliers": true,
            "iterations": 1,
            "std_devs": 3,
            "use_iqr_filtering": false,
            "use_standard_deviation_filtering": false
        },
        "fit": "linear",
        "fn": 122,
        "include_baseline_error": true,
        "n": 122,
        "outlier_excluded": [],
        "reviewed": true,
        "user_excluded": [],
        "value": 0.15981373239024033
    },
    "Ar39": {
        "error": 0.013135676610811846,
        "error_type": "SEM",
        "filter_outliers_dict": {
            "filter_outliers": true,
            "iterations": 1,
            "std_devs": 3,
            "use_iqr_filtering": false,
            "use_standard_deviation_filtering": false
        },
        "fit": "linear",
        "fn": 122,
        "include_baseline_error": true,
        "n": 122,
        "outlier_excluded": [],
        "reviewed": true,
        "user_excluded": [],
        "value": 10.906865204962816
    },
    "Ar40": {
        "error": 0.01689704317295496,
        "error_type": "SEM",
        "filter_outliers_dict": {
            "filter_outliers": true,
            "iterations": 1,
            "std_devs": 3,
            "use_iqr_filtering": false,
            "use_standard_deviation_filtering": false
        },
        "fit": "linear",
        "fn": 122,
        "include_baseline_error": true,
        "n": 122,
        "outlier_excluded": [],
        "reviewed": true,
        "user_excluded": [],
        "value": 63.10858899200439
    },
    "Ar41": {
        "error": 0.062339465693795476,
        "error_type": "SEM",
        "filter_outliers_dict": {
            "filter_outliers": true,
            "iterations": 1,
            "std_devs": 2
        },
        "fit": "linear",
        "value": -0.39353583166501716
    }
}